[
    {
        "articleStyle": 0,
        "customOrder": -10098457,
        "enableJs": true,
        "enabled": true,
        "enabledCookieJar": true,
        "header": "",
        "lastUpdateTime": 0,
        "loadWithBaseUrl": true,
        "ruleArticles": "",
        "ruleTitle": "",
        "singleUrl": true,
        "sourceComment": "（自用）精品网站合集",
        "sourceGroup": "",
        "sourceIcon": "",
        "sourceName": "在线工具",
        "sourceUrl": "https:\/\/tinywow.com\/"
    },
    {
        "articleStyle": 0,
        "customOrder": -10098457,
        "enableJs": true,
        "enabled": true,
        "enabledCookieJar": true,
        "header": "",
        "lastUpdateTime": 0,
        "loadWithBaseUrl": true,
        "ruleArticles": "",
        "ruleTitle": "",
        "singleUrl": true,
        "sourceComment": "（自用）精品网站合集",
        "sourceGroup": "",
        "sourceIcon": "",
        "sourceName": "星陨计划 Ark Re:Code",
        "sourceUrl": "https:\/\/game.erolabsshare.live\/app/d2302d69\/Ark_Re_Code"
    },
     {
        "articleStyle": 0,
        "customOrder": -10098457,
        "enableJs": true,
        "enabled": true,
        "enabledCookieJar": true,
        "header": "",
        "lastUpdateTime": 0,
        "loadWithBaseUrl": true,
        "ruleArticles": "",
        "ruleTitle": "",
        "singleUrl": true,
        "sourceComment": "（自用）精品网站合集",
        "sourceGroup": "",
        "sourceIcon": "",
        "sourceName": "互动小说",
        "sourceUrl": "https:\/\/i.meimoai8.com\/Avfcc"
    },
    {
        "articleStyle": 0,
        "customOrder": -10098457,
        "enableJs": true,
        "enabled": true,
        "enabledCookieJar": true,
        "header": "",
        "lastUpdateTime": 0,
        "loadWithBaseUrl": true,
        "ruleArticles": "",
        "ruleTitle": "",
        "singleUrl": true,
        "sourceComment": "（自用）精品网站合集",
        "sourceGroup": "",
        "sourceIcon": "",
        "sourceName": "好用网站合集",
        "sourceUrl": "https:\/\/lkssite.vip\/"
    },
    {
        "articleStyle": 0,
        "customOrder": -10098457,
        "enableJs": true,
        "enabled": true,
        "enabledCookieJar": true,
        "header": "",
        "lastUpdateTime": 0,
        "loadWithBaseUrl": true,
        "ruleArticles": "",
        "ruleTitle": "",
        "singleUrl": true,
        "sourceComment": "（自用）精品网站合集",
        "sourceGroup": "",
        "sourceIcon": "",
        "sourceName": "互联网资源",
        "sourceUrl": "https:\/\/www.lovejay.top\/#"
    }
]